nomina/__init__.py
nomina/account_view.py
nomina/bean_query.py
nomina/beancount_ledger.py
nomina/beanquery_cmd.py
nomina/book_view.py
nomina/bzv.py
nomina/bzv_ledger.py
nomina/converter.py
nomina/date_utils.py
nomina/file_formats.py
nomina/gnc_ledger.py
nomina/gnucash.py
nomina/ledger.py
nomina/money_zip.py
nomina/msmoney.py
nomina/msmoney_ledger.py
nomina/nomina_beancount.py
nomina/nomina_cmd.py
nomina/nomina_converter.py
nomina/qif.py
nomina/qif_ledger.py
nomina/stats.py
nomina/version.py
nomina/webserver.py
nomina_examples/FMQifTest2023-10-18.qif
nomina_examples/empty.yaml
nomina_examples/empty_sqlite.gnucash
nomina_examples/empty_xml.gnucash
nomina_examples/example.beancount
nomina_examples/expenses.qif
nomina_examples/expenses.yaml
nomina_examples/expenses2024.yaml
nomina_examples/expenses2024_bzv.json
nomina_examples/expenses2024_bzv.yaml
nomina_examples/expenses2024_xml.gnucash
nomina_examples/expenses_sqlite.gnucash
nomina_examples/expenses_xml.gnucash
nomina_examples/ledger.puml
nomina_examples/qifparser_test_file.qif
nomina_examples/qifparser_test_file.yaml
nomina_examples/qifparser_test_file_xml.gnucash
nomina_examples/queries.yaml
nomina_examples/sample_microsoft_money.zip
nomina_examples/simple_sample.yaml
nomina_examples/simple_sample_xml.gnucash
nomina_examples/taxes2022_bzv.json
pynomina-0.1.0.dist-info/METADATA
pynomina-0.1.0.dist-info/WHEEL
pynomina-0.1.0.dist-info/entry_points.txt
pynomina-0.1.0.dist-info/licenses/LICENSE
pynomina-0.1.0.dist-info/RECORD
