Metadata-Version: 2.4
Name: pynomina
Version: 0.1.0
Summary: Personal finance management utility
Project-URL: Home, https://github.com/WolfgangFahl/pynomina
Project-URL: Documentation, https://wiki.bitplan.com/index.php/pynomina
Project-URL: Source, https://github.com/WolfgangFahl/pynomina
Author-email: Wolfgang Fahl <wf@bitplan.com>
Maintainer-email: Wolfgang Fahl <wf@bitplan.com>
License-Expression: Apache-2.0
License-File: LICENSE
Keywords: finance,management,money,nicegui
Classifier: Development Status :: 4 - Beta
Classifier: Environment :: Web Environment
Classifier: Intended Audience :: Developers
Classifier: Intended Audience :: Education
Classifier: Intended Audience :: Science/Research
Classifier: License :: OSI Approved :: Apache Software License
Classifier: Operating System :: OS Independent
Classifier: Programming Language :: Python :: 3 :: Only
Classifier: Programming Language :: Python :: 3.10
Classifier: Programming Language :: Python :: 3.11
Classifier: Programming Language :: Python :: 3.12
Classifier: Programming Language :: Python :: 3.13
Classifier: Topic :: Software Development :: Libraries :: Python Modules
Requires-Python: >=3.10
Requires-Dist: beancount>=3.1.0
Requires-Dist: beanquery==0.1.0
Requires-Dist: chardet>=5.2.0
Requires-Dist: networkx>=3.3
Requires-Dist: ngwidgets>=0.26.1
Requires-Dist: py-sidif>=0.2.0
Requires-Dist: pybasemkit>=0.0.2
Requires-Dist: pylodstorage>=0.16.4
Requires-Dist: pymogwai>=0.0.9
Requires-Dist: tabulate>=0.9.0
Requires-Dist: xsdata>=24.9
Provides-Extra: test
Requires-Dist: green; extra == 'test'
